pdd/__init__.py
pdd/agentic_architecture.py
pdd/agentic_architecture_orchestrator.py
pdd/agentic_bug.py
pdd/agentic_bug_orchestrator.py
pdd/agentic_change.py
pdd/agentic_change_orchestrator.py
pdd/agentic_common.py
pdd/agentic_crash.py
pdd/agentic_e2e_fix.py
pdd/agentic_e2e_fix_orchestrator.py
pdd/agentic_fix.py
pdd/agentic_langtest.py
pdd/agentic_test.py
pdd/agentic_test_generate.py
pdd/agentic_test_orchestrator.py
pdd/agentic_update.py
pdd/agentic_verify.py
pdd/architecture_sync.py
pdd/auth_service.py
pdd/auto_deps_main.py
pdd/auto_include.py
pdd/auto_update.py
pdd/bug_main.py
pdd/bug_to_unit_test.py
pdd/change.py
pdd/change_main.py
pdd/cli.py
pdd/cmd_test_main.py
pdd/code_generator.py
pdd/code_generator_main.py
pdd/comment_line.py
pdd/config_resolution.py
pdd/conflicts_in_prompts.py
pdd/conflicts_main.py
pdd/construct_paths.py
pdd/context_generator.py
pdd/context_generator_main.py
pdd/continue_generation.py
pdd/crash_main.py
pdd/detect_change.py
pdd/detect_change_main.py
pdd/edit_file.py
pdd/find_section.py
pdd/fix_code_loop.py
pdd/fix_code_module_errors.py
pdd/fix_error_loop.py
pdd/fix_errors_from_unit_tests.py
pdd/fix_main.py
pdd/fix_verification_errors.py
pdd/fix_verification_errors_loop.py
pdd/fix_verification_main.py
pdd/generate_output_paths.py
pdd/generate_test.py
pdd/get_comment.py
pdd/get_extension.py
pdd/get_jwt_token.py
pdd/get_language.py
pdd/get_run_command.py
pdd/get_test_command.py
pdd/git_update.py
pdd/increase_tests.py
pdd/incremental_code_generator.py
pdd/insert_includes.py
pdd/install_completion.py
pdd/llm_invoke.py
pdd/load_prompt_template.py
pdd/logo_animation.py
pdd/mcp_config.json
pdd/operation_log.py
pdd/path_resolution.py
pdd/pdd_completion.fish
pdd/pdd_completion.sh
pdd/pdd_completion.zsh
pdd/pin_example_hack.py
pdd/postprocess.py
pdd/postprocess_0.py
pdd/preprocess.py
pdd/preprocess_main.py
pdd/process_csv_change.py
pdd/pytest_output.py
pdd/python_env_detector.py
pdd/remote_session.py
pdd/render_mermaid.py
pdd/setup_tool.py
pdd_cli-0.0.135.dist-info/licenses/LICENSE
pdd_cli-0.0.135.dist-info/METADATA
pdd_cli-0.0.135.dist-info/WHEEL
pdd_cli-0.0.135.dist-info/entry_points.txt
pdd_cli-0.0.135.dist-info/top_level.txt
pdd_cli-0.0.135.dist-info/RECORD
