Metadata-Version: 2.4
Name: pdd-cli
Version: 0.0.135
Summary: PDD (Prompt-Driven Development) Command Line Interface
Author: Greg Tanaka
Author-email: glt@alumni.caltech.edu
License: MIT
Project-URL: Homepage, https://github.com/promptdriven/pdd.git
Project-URL: Repository, https://github.com/promptdriven/pdd.git
Project-URL: Issue-Tracker, https://github.com/promptdriven/pdd/issues
Keywords: prompt-driven development,code generation,AI,LLM,unit testing,software development
Classifier: Development Status :: 3 - Alpha
Classifier: Intended Audience :: Developers
Classifier: License :: OSI Approved :: MIT License
Classifier: Programming Language :: Python :: 3.11
Classifier: Programming Language :: Python :: 3.12
Classifier: Topic :: Software Development :: Code Generators
Classifier: Topic :: Scientific/Engineering :: Artificial Intelligence
Requires-Python: >=3.12
License-File: LICENSE
Requires-Dist: GitPython==3.1.44
Requires-Dist: Requests==2.32.4
Requires-Dist: aiofiles==24.1.0
Requires-Dist: click==8.1.7
Requires-Dist: firecrawl-py==2.5.3
Requires-Dist: firebase_admin==6.6.0
Requires-Dist: keyring==25.6.0
Requires-Dist: nest_asyncio==1.6.0
Requires-Dist: pandas==2.2.3
Requires-Dist: psutil>=7.0.0
Requires-Dist: pydantic==2.11.4
Requires-Dist: litellm[caching]>=1.80.0
Requires-Dist: lxml>=5.0.0
Requires-Dist: rich==14.0.0
Requires-Dist: semver==3.0.2
Requires-Dist: setuptools
Requires-Dist: pytest==8.3.5
Requires-Dist: pytest-cov==5.0.0
Requires-Dist: boto3==1.35.99
Requires-Dist: google-cloud-aiplatform>=1.3
Requires-Dist: openai>=1.99.5
Requires-Dist: pillow-heif==1.1.1
Requires-Dist: Pillow==12.0.0
Requires-Dist: textual
Requires-Dist: python-dotenv==1.1.0
Requires-Dist: PyYAML==6.0.1
Requires-Dist: jsonschema==4.23.0
Requires-Dist: z3-solver==4.14.1.0
Requires-Dist: fastapi>=0.115.0
Requires-Dist: uvicorn[standard]>=0.32.0
Requires-Dist: websockets>=13.0
Requires-Dist: watchdog>=4.0.0
Requires-Dist: tiktoken>=0.7.0
Provides-Extra: dev
Requires-Dist: commitizen; extra == "dev"
Requires-Dist: pytest-cov; extra == "dev"
Requires-Dist: pytest-testmon; extra == "dev"
Requires-Dist: pytest-xdist; extra == "dev"
Requires-Dist: pytest-mock; extra == "dev"
Requires-Dist: pytest-asyncio; extra == "dev"
Requires-Dist: build; extra == "dev"
Requires-Dist: twine; extra == "dev"
Requires-Dist: httpx==0.28.1; extra == "dev"
Dynamic: license-file
